sklearn_whiskers/__init__.py
sklearn_whiskers/outliers/StandardOutliers.py
sklearn_whiskers/outliers/WhiskerOutliers.py
sklearn_whiskers/outliers/__init__.py
scikit_learn_whiskers-0.3.0.dist-info/LICENSE
scikit_learn_whiskers-0.3.0.dist-info/METADATA
scikit_learn_whiskers-0.3.0.dist-info/WHEEL
scikit_learn_whiskers-0.3.0.dist-info/top_level.txt
scikit_learn_whiskers-0.3.0.dist-info/RECORD
