Metadata-Version: 2.1
Name: scikit-learn-whiskers
Version: 0.3.0
Summary: Tools aimed to facilitate some datascience and machine learning tasks.
Author-email: Martin Carlos Araya <martinaraya@gmail.com>
License: MIT License
Project-URL: Homepage, https://github.com/ayaranitram/scikit-learn-whiskers
Project-URL: Bug Tracker, https://github.com/ayaranitram/unyts/scikit-learn-whiskers
Classifier: Programming Language :: Python :: 3.7
Classifier: Programming Language :: Python :: 3.8
Classifier: Programming Language :: Python :: 3.9
Classifier: Programming Language :: Python :: 3.10
Classifier: Programming Language :: Python :: 3.11
Classifier: License :: OSI Approved :: MIT License
Classifier: Operating System :: OS Independent
Requires-Python: >=3.7
License-File: LICENSE
